reflex_firebase/__init__.py
reflex_firebase/auth_form.py
reflex_firebase/auth_state.py
reflex_firebase/config.py
reflex_firebase/pyredantic.py
reflex_firebase-0.0.11.dist-info/METADATA
reflex_firebase-0.0.11.dist-info/WHEEL
reflex_firebase-0.0.11.dist-info/RECORD
