Metadata-Version: 2.1
Name: reflex-firebase
Version: 0.0.11
Summary: 
License: MIT
Author: neka-nat
Author-email: nekanat.stock@gmail.com
Requires-Python: >=3.9,<4.0
Classifier: License :: OSI Approved :: MIT License
Classifier: Programming Language :: Python :: 3
Classifier: Programming Language :: Python :: 3.9
Classifier: Programming Language :: Python :: 3.10
Classifier: Programming Language :: Python :: 3.11
Classifier: Programming Language :: Python :: 3.12
Requires-Dist: pyrebase4 (>=4.8.0,<5.0.0)
Requires-Dist: python-dotenv (>=1.0.1,<2.0.0)
Requires-Dist: reflex (>=0.5.5,<0.6.0)
